AnilistPython/__init__.py
AnilistPython/anilistpython_info.py
AnilistPython/anime.py
AnilistPython/character.py
AnilistPython/deep_search.py
AnilistPython/manga.py
AnilistPython/query_strings.py
AnilistPython/retrieve_data.py
AnilistPython/retrieve_id.py
AnilistPython/test_cases.py
AnilistPython/databases/__init__.py
AnilistPython/databases/cipher.py
AnilistPython/databases/database_anime_retrieval.py
AnilistPython/databases/search_engine.py
AnilistPython/databases/anime_database_files/anime_by_genre.json
AnilistPython/databases/anime_database_files/anime_by_id.json
AnilistPython/databases/anime_database_files/anime_by_id_cache.json
AnilistPython/databases/anime_database_files/anime_by_score.json
AnilistPython/databases/anime_database_files/anime_by_tag.json
AnilistPython/databases/anime_database_files/anime_by_tag_cache.json
AnilistPython/databases/anime_database_files/anime_by_year.json
AnilistPython/legacy_files/__init__.py
AnilistPython/legacy_files/bot_support.py
AnilistPython/legacy_files/multi_processing.py
AnilistPython/logs/__init__.py
AnilistPython/logs/internet_latency_identifier.py
AnilistPython/logs/log_data.py
AnilistPython/logs/logs.json
AnilistPython/logs/report_logs.py
AnilistPython/logs/setup.json
AnilistPython/logs/setup_module.py
AnilistPython/support_files/__init__.py
AnilistPython/support_files/constants.py
AnilistPython/support_files/deep_search_exceptions.py
AnilistPython/support_files/test.py
AnilistPython/support_files/translate.py
AnilistPython/support_files/translate_structure.py
AnilistPython-0.1.3.dist-info/METADATA
AnilistPython-0.1.3.dist-info/WHEEL
AnilistPython-0.1.3.dist-info/top_level.txt
AnilistPython-0.1.3.dist-info/RECORD
