Metadata-Version: 2.1
Name: AnilistPython
Version: 0.1.3
Summary: Anilist Python module for searching up anime, manga, characters info.
Home-page: https://github.com/ReZeroE/AnilistPython
Author: Kevin L. (ReZeroK)
Author-email: kevinliu@vt.edu
License: MIT Licence (MIT)
Keywords: python,anime,anilist,manga,light novel,characters,ReZeroK,search anime,python anime,anime python,anilist python
Platform: UNKNOWN
Classifier: Development Status :: 5 - Production/Stable
Classifier: License :: OSI Approved :: MIT License
Classifier: Intended Audience :: Developers
Classifier: Programming Language :: Python :: 3
Classifier: Operating System :: Unix
Classifier: Operating System :: MacOS :: MacOS X
Classifier: Operating System :: Microsoft :: Windows
